<?xml version="1.0" encoding="utf-8" ?>
<dwsync>
<file name="AbsoluteLayout.js" server="173.236.120.66//websites/discoverfundraising.com/" local="129911220000000000" remote="129911220000000000" />
<file name="AccordionLayout.js" server="173.236.120.66//websites/discoverfundraising.com/" local="129911220000000000" remote="129911220000000000" />
<file name="AnchorLayout.js" server="173.236.120.66//websites/discoverfundraising.com/" local="129911220000000000" remote="129911220000000000" />
<file name="AutoLayout.js" server="173.236.120.66//websites/discoverfundraising.com/" local="129911220000000000" remote="129911220000000000" />
<file name="BorderLayout.js" server="173.236.120.66//websites/discoverfundraising.com/" local="129911220000000000" remote="129911220000000000" />
<file name="BoxLayout.js" server="173.236.120.66//websites/discoverfundraising.com/" local="129911220000000000" remote="129911220000000000" />
<file name="CardLayout.js" server="173.236.120.66//websites/discoverfundraising.com/" local="129911220000000000" remote="129911220000000000" />
<file name="ColumnLayout.js" server="173.236.120.66//websites/discoverfundraising.com/" local="129911220000000000" remote="129911220000000000" />
<file name="ContainerLayout.js" server="173.236.120.66//websites/discoverfundraising.com/" local="129911220000000000" remote="129911220000000000" />
<file name="FitLayout.js" server="173.236.120.66//websites/discoverfundraising.com/" local="129911220000000000" remote="129911220000000000" />
<file name="FormLayout.js" server="173.236.120.66//websites/discoverfundraising.com/" local="129911220000000000" remote="129911220000000000" />
<file name="HBoxLayout.js" server="173.236.120.66//websites/discoverfundraising.com/" local="129911220000000000" remote="129911220000000000" />
<file name="MenuLayout.js" server="173.236.120.66//websites/discoverfundraising.com/" local="129911220000000000" remote="129911220000000000" />
<file name="TableLayout.js" server="173.236.120.66//websites/discoverfundraising.com/" local="129911220000000000" remote="129911220000000000" />
<file name="ToolbarLayout.js" server="173.236.120.66//websites/discoverfundraising.com/" local="129911220000000000" remote="129911220000000000" />
<file name="VBoxLayout.js" server="173.236.120.66//websites/discoverfundraising.com/" local="129911220000000000" remote="129911220000000000" />
</dwsync>